{
    "chloroform": [
        {
            "exp_ppm": 77,
            "Jv": [
                64
            ]
        }
    ],
    "dimethylsulfoxide": [
        {
            "exp_ppm": 39.51,
            "Jv": [
                42,
                42,
                42
            ]
        }
    ],
    "methanol": [
        {
            "exp_ppm": 49.15,
            "Jv": [
                42.8,
                42.8,
                42.8
            ]
        }
    ],
    "pyridine": [
        {
            "exp_ppm": 150.35,
            "Jv": [
                55,
                55
            ]
        },
        {
            "exp_ppm": 135.91,
            "Jv": [
                49,
                49
            ]
        },
        {
            "exp_ppm": 123.87,
            "Jv": [
                50,
                50
            ]
        }
    ],
    "benzene": [
        {
            "exp_ppm": 128.39,
            "Jv": 24.3
        }
    ]
}